ai_marketplace_monitor/__init__.py
ai_marketplace_monitor/ai.py
ai_marketplace_monitor/cli.py
ai_marketplace_monitor/config.py
ai_marketplace_monitor/config.toml
ai_marketplace_monitor/email.html.j2
ai_marketplace_monitor/email_notify.py
ai_marketplace_monitor/facebook.py
ai_marketplace_monitor/listing.py
ai_marketplace_monitor/marketplace.py
ai_marketplace_monitor/monitor.py
ai_marketplace_monitor/notification.py
ai_marketplace_monitor/ntfy.py
ai_marketplace_monitor/pushbullet.py
ai_marketplace_monitor/pushover.py
ai_marketplace_monitor/py.typed
ai_marketplace_monitor/region.py
ai_marketplace_monitor/telegram.py
ai_marketplace_monitor/user.py
ai_marketplace_monitor/utils.py
ai_marketplace_monitor-0.9.11.dist-info/METADATA
ai_marketplace_monitor-0.9.11.dist-info/WHEEL
ai_marketplace_monitor-0.9.11.dist-info/entry_points.txt
ai_marketplace_monitor-0.9.11.dist-info/licenses/LICENSE
ai_marketplace_monitor-0.9.11.dist-info/RECORD
