Metadata-Version: 2.4
Name: ai-marketplace-monitor
Version: 0.9.11
Summary: An AI-based tool for monitoring facebook marketplace
Project-URL: Homepage, https://github.com/BoPeng/ai-marketplace-monitor
Project-URL: Repository, https://github.com/BoPeng/ai-marketplace-monitor
Project-URL: Documentation, https://ai-marketplace-monitor.readthedocs.io
Project-URL: Bug Tracker, https://github.com/BoPeng/ai-marketplace-monitor/issues
Author-email: Bo Peng <ben.bob@gmail.com>
License-File: LICENSE
Keywords: ai-marketplace-monitor
Classifier: Development Status :: 2 - Pre-Alpha
Classifier: Intended Audience :: Developers
Classifier: License :: OSI Approved :: GNU Affero General Public License v3
Classifier: Natural Language :: English
Classifier: Programming Language :: Python :: 3
Classifier: Programming Language :: Python :: 3.10
Classifier: Programming Language :: Python :: 3.11
Classifier: Programming Language :: Python :: 3.12
Requires-Python: >=3.10
Requires-Dist: currencyconverter>=0.18.0
Requires-Dist: diskcache>=5.6.3
Requires-Dist: humanize>=4.0.0
Requires-Dist: inflect>=7.0.0
Requires-Dist: jinja2>=3.0.0
Requires-Dist: openai>=1.24.0
Requires-Dist: parsedatetime>=2.5
Requires-Dist: pillow>=10.0.0
Requires-Dist: pip-audit>=2.9.0
Requires-Dist: playwright>=1.41.0
Requires-Dist: pushbullet-py>=0.12.0
Requires-Dist: pyparsing>=3.1.0
Requires-Dist: python-telegram-bot>=22.3
Requires-Dist: requests>=2.30.0
Requires-Dist: rich>=13.7.0
Requires-Dist: safety>=3.5.2
Requires-Dist: schedule>=1.2.2
Requires-Dist: tomli==2.2.1; python_version < '3.11'
Requires-Dist: typer<0.18.0,>=0.15.1
Requires-Dist: watchdog>=4.0.0
Provides-Extra: dev
Requires-Dist: build>=1.0.0; extra == 'dev'
Requires-Dist: bump2version>=1.0.1; extra == 'dev'
Requires-Dist: invoke>=2.2.0; extra == 'dev'
Requires-Dist: pip-audit>=2.9.0; extra == 'dev'
Requires-Dist: pre-commit>=4.0.1; extra == 'dev'
Requires-Dist: twine>=5.0.0; extra == 'dev'
Requires-Dist: watchdog[watchmedo]>=6.0.0; extra == 'dev'
Provides-Extra: docs
Requires-Dist: furo>=2024.1.29; extra == 'docs'
Requires-Dist: linkify-it-py>=2.0.0; extra == 'docs'
Requires-Dist: myst-parser>=3.0.0; extra == 'docs'
Requires-Dist: sphinx-copybutton>=0.5.2; extra == 'docs'
Requires-Dist: sphinx>=8.1.3; extra == 'docs'
Requires-Dist: sphinxext-opengraph>=0.9.0; extra == 'docs'
Provides-Extra: linters
Requires-Dist: black<26.0,>=24.10; extra == 'linters'
Requires-Dist: isort<7.0.0,>=5.13.2; extra == 'linters'
Requires-Dist: ruff<0.14.0,>=0.9.2; extra == 'linters'
Provides-Extra: pynput
Requires-Dist: pynput>=1.7.0; extra == 'pynput'
Provides-Extra: security
Requires-Dist: safety>=3.2.11; extra == 'security'
Provides-Extra: test
Requires-Dist: coverage[toml]>=7.6.7; extra == 'test'
Requires-Dist: pytest-cov>=6.0.0; extra == 'test'
Requires-Dist: pytest-playwright>=0.7.0; extra == 'test'
Requires-Dist: pytest>=8.3.3; extra == 'test'
Requires-Dist: xdoctest>=1.2.0; extra == 'test'
Provides-Extra: typing
Requires-Dist: mypy>=1.13.0; extra == 'typing'
